{
  "project_info": {
    "project_number": "367825906031",
    "project_id": "myproject-aa7f2",
    "storage_bucket": "myproject-aa7f2.appspot.com"
  },
  "client": [
    {
      "client_info": {
        "mobilesdk_app_id": "1:367825906031:android:f1c143c045bf12f362609a",
        "android_client_info": {
          "package_name": "com.example.flutter_applicationhuak_1"
        }
      },
      "oauth_client": [],
      "api_key": [
        {
          "current_key": "AIzaSyAFmrLyRw_pRn988m4jMG-XZJH2VypbZcc"
        }
      ],
      "services": {
        "appinvite_service": {
          "other_platform_oauth_client": []
        }
      }
    },
    {
      "client_info": {
        "mobilesdk_app_id": "1:367825906031:android:19130e24d51a8c9f62609a",
        "android_client_info": {
          "package_name": "com.example.work"
        }
      },
      "oauth_client": [],
      "api_key": [
        {
          "current_key": "AIzaSyAFmrLyRw_pRn988m4jMG-XZJH2VypbZcc"
        }
      ],
      "services": {
        "appinvite_service": {
          "other_platform_oauth_client": []
        }
      }
    }
  ],
  "configuration_version": "1"
}